ragflow_toolkit/__init__.py
ragflow_toolkit/agent.py
ragflow_toolkit/chat.py
ragflow_toolkit/client.py
ragflow_toolkit/config.py
ragflow_toolkit/dataset.py
ragflow_toolkit/exceptions.py
ragflow_toolkit/types.py
ragflow_toolkit/utils.py
ragflow_toolkit-0.1.1.dist-info/METADATA
ragflow_toolkit-0.1.1.dist-info/WHEEL
ragflow_toolkit-0.1.1.dist-info/top_level.txt
ragflow_toolkit-0.1.1.dist-info/RECORD
