Metadata-Version: 2.4
Name: ragflow-toolkit
Version: 0.1.1
Summary: Django ORM 风格的 ragflow-sdk 封装
Author-email: langxu <langxu2023@outlook.com>
Requires-Python: >=3.12
Requires-Dist: pydantic>=2.11.7
Requires-Dist: pytest>=8.4.1
Requires-Dist: ragflow-sdk>=0.19.1
